qrun/__init__.py
qrun/__main__.py
qrun/handlers.py
qrun/qrun-util
qrun/scripts.py
qrun/utils.py
qrun-0.6.0.dist-info/METADATA
qrun-0.6.0.dist-info/WHEEL
qrun-0.6.0.dist-info/entry_points.txt
qrun-0.6.0.dist-info/licenses/LICENSE.md
qrun-0.6.0.dist-info/RECORD
