Metadata-Version: 2.3
Name: qrun
Version: 0.6.0
Summary: A small utility for running multiple jobs in parallel or series.
Author-email: CD Clark III <clifton.clark@gmail.com>
Requires-Python: >=3.8
